djangocms_light_gallery-0.0.7.dist-info/DESCRIPTION.rst
djangocms_light_gallery-0.0.7.dist-info/METADATA
djangocms_light_gallery-0.0.7.dist-info/RECORD
djangocms_light_gallery-0.0.7.dist-info/WHEEL
djangocms_light_gallery-0.0.7.dist-info/metadata.json
djangocms_light_gallery-0.0.7.dist-info/top_level.txt
light_gallery/__init__.py
light_gallery/admin.py
light_gallery/cms_plugins.py
light_gallery/models.py
light_gallery/tests.py
light_gallery/views.py
light_gallery/migrations/0001_initial.py
light_gallery/migrations/0002_lightgallery_zoom.py
light_gallery/migrations/0003_lightgallery_fullscreen.py
light_gallery/migrations/0004_lightgallery_thumbnails.py
light_gallery/migrations/0005_auto_20160727_2006.py
light_gallery/migrations/0006_auto_20160729_1644.py
light_gallery/migrations/0007_auto_20160729_2046.py
light_gallery/migrations/0008_auto_20160729_2130.py
light_gallery/migrations/0009_auto_20160729_2222.py
light_gallery/migrations/0010_auto_20160729_2236.py
light_gallery/migrations/0011_auto_20160731_2122.py
light_gallery/migrations/0012_auto_20160731_2135.py
light_gallery/migrations/0013_auto_20170617_2115.py
light_gallery/migrations/0014_lightgallery_showthumbbydefault.py
light_gallery/migrations/0015_auto_20170617_2133.py
light_gallery/migrations/__init__.py
light_gallery/static/css/lg-fb-comment-box.css
light_gallery/static/css/lg-fb-comment-box.min.css
light_gallery/static/css/lg-transitions.css
light_gallery/static/css/lg-transitions.min.css
light_gallery/static/css/lightgallery.css
light_gallery/static/css/lightgallery.min.css
light_gallery/static/fonts/lg.eot
light_gallery/static/fonts/lg.svg
light_gallery/static/fonts/lg.ttf
light_gallery/static/fonts/lg.woff
light_gallery/static/img/loading.gif
light_gallery/static/img/video-play.png
light_gallery/static/img/vimeo-play.png
light_gallery/static/img/youtube-play.png
light_gallery/static/js/lg-autoplay.js
light_gallery/static/js/lg-autoplay.min.js
light_gallery/static/js/lg-fullscreen.js
light_gallery/static/js/lg-fullscreen.min.js
light_gallery/static/js/lg-hash.js
light_gallery/static/js/lg-hash.min.js
light_gallery/static/js/lg-pager.js
light_gallery/static/js/lg-pager.min.js
light_gallery/static/js/lg-share.min.js
light_gallery/static/js/lg-thumbnail.js
