Metadata-Version: 2.0
Name: djangocms-light-gallery
Version: 0.0.7
Summary: Light Gallery plugin for django CMS
Home-page: https://github.com/andyklimczak/djangocms-light-gallery
Author: Andy Klimczak
Author-email: andyklimczak@fastmail.com
License: MIT
Platform: UNKNOWN
Requires-Dist: django (>=1.8)
Requires-Dist: django-cms (>=3.0)
Requires-Dist: django-filer
Requires-Dist: django-sekizai
Requires-Dist: easy-thumbnails
